pmacs/__init__.py
pmacs-0.0.1.dist-info/LICENSE
pmacs-0.0.1.dist-info/METADATA
pmacs-0.0.1.dist-info/WHEEL
pmacs-0.0.1.dist-info/top_level.txt
pmacs-0.0.1.dist-info/RECORD
