Metadata-Version: 2.1
Name: pmacs
Version: 0.0.1
Summary: Python editing MACroS
Home-page: https://github.com/bartlbrown/pmacs
Author: Bart L. Brown
Author-email: bartonlbrown@gmail.com
License: UNKNOWN
Platform: UNKNOWN
Classifier: Programming Language :: Python :: 3
Classifier: License :: OSI Approved :: MIT License
Classifier: Operating System :: OS Independent
